{
    "dictionary":[
        {
            "word":"assuage",
            "definition":"to calm, to ease, to make less severe"
        },
        {
            "word":"piety",
            "definition":"devotion and reverence to God"
        },
        {
            "word":"dictum",
            "definition":"an order or command from an authority"
        },
        {
            "word":"taciturn",
            "definition":"quiet, reserved"
        },
        {
            "word":"quaint",
            "definition":"unusual in a charming way"
        },
        {
            "word":"malevolent",
            "definition":"evil"
        },
        {
            "word":"predilection",
            "definition":"preference"
        },
        {
            "word":"domicile",
            "definition":"a home; residence"
        },
        {
            "word":"profane",
            "definition":"showing contempt toward sacred things"
        },
        {
            "word":"terrain",
            "definition":"of the earth or relating to the earth"
        },
        {
            "word":"indigenous",
            "definition":"native to a certain area"
        },
        {
            "word":"diminutive",
            "definition":"small, miniature"
        },
        {
            "word":"fractious",
            "definition":"unruly; out of control; breaking the peace"
        },
        {
            "word":"disapprobation",
            "definition":"disapproval; condemnation"
        },
        {
            "word":"auspicious",
            "definition":"favorable"
        },
        {
            "word":"palette",
            "definition":"board on which a painter mixes paints"
        },
        {
            "word":"benevolence",
            "definition":"kindness, generosity"
        },
        {
            "word":"hone",
            "definition":"to sharpen; to make more effective"
        },
        {
            "word":"caricature",
            "definition":"a portrayal where features are exaggerated"
        },
        {
            "word":"inordinate",
            "definition":"exceeding reasonable limits, excessive"
        },
        {
            "word":"ingenious",
            "definition":"inventive, clever, brilliant"
        },
        {
            "word":"innate",
            "definition":"existing from birth"
        },
        {
            "word":"guileless",
            "definition":"without deceit"
        },
        {
            "word":"fanatic",
            "definition":"one that is extremely enthusiastic or zealous"
        },
        {
            "word":"tentative",
            "definition":"uncertain, not fully worked out or confirmed"
        },
        {
            "word":"rudiment",
            "definition":"an essential element or skill, also the early stages of development"
        },
        {
            "word":"articulate",
            "definition":"to speak distinctly; expressing oneself clearly"
        },
        {
            "word":"melancholy",
            "definition":"depression of spirits"
        },
        {
            "word":"palliate",
            "definition":"to ease pain, guilt or intensity"
        },
        {
            "word":"rectitude",
            "definition":"state of moral integrity"
        },
        {
            "word":"tranquil",
            "definition":"peaceful, calm"
        },
        {
            "word":"protrude",
            "definition":"to stick out"
        },
        {
            "word":"propensity",
            "definition":"preference, natural inclination"
        },
        {
            "word":"frivolous",
            "definition":"Lacking in seriousness or importance"
        },
        {
            "word":"propel",
            "definition":"to drive or push forward"
        },
        {
            "word":"formidable",
            "definition":"menacing, causing fear or awe"
        },
        {
            "word":"obilque",
            "definition":"slanting, indirect, evasive, devious, misleading"
        },
        {
            "word":"edification",
            "definition":"spiritual, moral or intellectual improvement"
        },
        {
            "word":"reverent",
            "definition":"honorable, regarding with respect"
        },
        {
            "word":"infallible",
            "definition":"incapable of error"
        },
        {
            "word":"placid",
            "definition":"calm, peaceful"
        },
        {
            "word":"begrudge",
            "definition":"to give reluctantly, to envy a possession or one's enjoyment"
        },
        {
            "word":"ominous",
            "definition":"threatening"
        },
        {
            "word":"vivid",
            "definition":"bright, distinct, and clear"
        },
        {
            "word":"oblivion",
            "definition":"state of being forgotten"
        },
        {
            "word":"succinct",
            "definition":"brief and compact"
        },
        {
            "word":"acquiesce",
            "definition":"to give in, to comply"
        },
        {
            "word":"elucidate",
            "definition":"to make clear, to explain"
        },
        {
            "word":"unobtrusive",
            "definition":"not readily noticeable, inconspicuous"
        },
        {
            "word":"turbulence",
            "definition":"wild or disturbing activity"
        },
        {
            "word":"corroboration",
            "definition":"confirmation"
        },
        {
            "word":"congenital",
            "definition":"existing from birth or dating at birth"
        },
        {
            "word":"acrimonious",
            "definition":"caustic, bitter"
        },
        {
            "word":"serene",
            "definition":"calm or placid or tranquil"
        },
        {
            "word":"complacency",
            "definition":"the state of being self-satisfied"
        },
        {
            "word":"stealthy",
            "definition":"acting in a secret and sneaky way"
        },
        {
            "word":"impudent",
            "definition":"disrespectful, characterized by improper bold behavior"
        },
        {
            "word":"fraudulent",
            "definition":"deceitful; portrayed as genuine but is really an imposter"
        },
        {
            "word":"arid",
            "definition":"very dry"
        },
        {
            "word":"unmitigated",
            "definition":"absolute, not made less severe or intense"
        },
        {
            "word":"temerity",
            "definition":"boldness that is reckless"
        },
        {
            "word":"furtive",
            "definition":"secret in an underhanded way"
        },
        {
            "word":"sordid",
            "definition":"filthy, foul"
        },
        {
            "word":"drone",
            "definition":"speaking in a monotonous tone; a continuous low humming sound"
        },
        {
            "word":"impertinent",
            "definition":"insolently rude, not within the proper bounds of good taste or manners"
        },
        {
            "word":"recluse",
            "definition":"a person who lives in solitude, a hermit"
        },
        {
            "word":"enunciate",
            "definition":"to pronounce clearly"
        },
        {
            "word":"savory",
            "definition":"appetizing"
        },
        {
            "word":"irascible",
            "definition":"irritable, easily angered, cranky, cross"
        },
        {
            "word":"lament",
            "definition":"to mourn or to express sorrow in a demonstrative manner"
        },
        {
            "word":"austere",
            "definition":"Strict"
        },
        {
            "word":"biased",
            "definition":"favoritism"
        },
        {
            "word":"crude",
            "definition":"Rude"
        },
        {
            "word":"disillusioned",
            "definition":"depressed and disappointed"
        },
        {
            "word":"disparaging",
            "definition":"expressive of low opinion"
        },
        {
            "word":"dubious",
            "definition":"suspicious"
        },
        {
            "word":"familial",
            "definition":"family"
        },
        {
            "word":"hypercritical",
            "definition":"overcritical; too severe in judgement"
        },
        {
            "word":"impudent",
            "definition":"rude"
        },
        {
            "word":"judicious",
            "definition":"serious, wise"
        },
        {
            "word":"objective",
            "definition":"looking towards a goal"
        },
        {
            "word":"priggish",
            "definition":"straight-laced, stuffy"
        },
        {
            "word":"rambunctious",
            "definition":"Loud, annoying"
        },
        {
            "word":"rash",
            "definition":"Loud"
        },
        {
            "word":"raucous",
            "definition":"Loud, crazy"
        },
        {
            "word":"reverent",
            "definition":"Honorable"
        },
        {
            "word":"sardonic",
            "definition":"bitterly sarcastic"
        },
        {
            "word":"satirical",
            "definition":"funny"
        },
        {
            "word":"sophomoric",
            "definition":"immature and overconfident"
        },
        {
            "word":"tractable",
            "definition":"easily managed or controlled"
        }
    ]
}